LICENSE.txt
MANIFEST.in
README.rst
setup.py
django_onetime.egg-info/PKG-INFO
django_onetime.egg-info/SOURCES.txt
django_onetime.egg-info/dependency_links.txt
django_onetime.egg-info/not-zip-safe
django_onetime.egg-info/top_level.txt
onetime/__init__.py
onetime/apps.py
onetime/fields.py
onetime/middleware.py
onetime/models.py
onetime/shortcuts.py
onetime/tests.py
onetime/views.py
onetime/migrations/0001_initial.py
onetime/migrations/0002_auto__add_field_onetimecallback_is_view.py
onetime/migrations/__init__.py