Metadata-Version: 1.0
Name: django-onetime
Version: 0.2.0
Summary: A reusable Django app that lets you call followup functions after an event has taken place.  (Such as two-factor authentication)
Home-page: http://bitbucket.org/mirusresearch/django-onetime
Author: Don Spaulding
Author-email: don@mirusresearch.com
License: MIT license, see LICENSE.txt
Platform: UNKNOWN
